bottle_pika.py
setup.py
bottle_pika.egg-info/PKG-INFO
bottle_pika.egg-info/SOURCES.txt
bottle_pika.egg-info/dependency_links.txt
bottle_pika.egg-info/requires.txt
bottle_pika.egg-info/top_level.txt