Metadata-Version: 1.0
Name: bottle-pika
Version: 0.1.0
Summary: Pika plugin module for Bottle microframework
Home-page: https://github.com/dbroudy/bottle-pika
Author: David Broudy
Author-email: dave@broudy.net
License: MIT
Keywords: bottle rabbitmq amqp pika messaging message queue
Platform: any
Classifier: Development Status :: 4 - Beta
Classifier: Environment :: Web Environment
Classifier: Framework :: Bottle
Classifier: Operating System :: OS Independent
Classifier: License :: OSI Approved :: MIT License
Classifier: Programming Language :: Python
Classifier: Topic :: Software Development :: Libraries :: Python Modules
